tamilmv_bot-0.2.1.dist-info/licenses/LICENSE
tamilmvbot/__init__.py
tamilmvbot/angel.py
tamilmv_bot-0.2.1.dist-info/METADATA
tamilmv_bot-0.2.1.dist-info/WHEEL
tamilmv_bot-0.2.1.dist-info/top_level.txt
tamilmv_bot-0.2.1.dist-info/RECORD
