Metadata-Version: 2.4
Name: tamilmv-bot
Version: 0.2.1
Summary: Telegram bot for downloading from 1Tamilmv Torrent magnet link
Home-page: https://github.com/SudoR2spr/1tamilmv_v2_Bot
Author: SudoR2spr
Author-email: wdzoneleech@gmail.com
License: MIT
Project-URL: Bug Reports, https://github.com/SudoR2spr/1tamilmv_v2_Bot/issues
Project-URL: Source, https://github.com/SudoR2spr/1tamilmv_v2_Bot
Keywords: telegram bot 1tamilmv movies torrent magnet link downloader
Platform: any
Classifier: Programming Language :: Python :: 3
Classifier: Programming Language :: Python :: 3.7
Classifier: Programming Language :: Python :: 3.8
Classifier: Programming Language :: Python :: 3.9
Classifier: Programming Language :: Python :: 3.10
Classifier: Programming Language :: Python :: 3.11
Classifier: Programming Language :: Python :: 3.12
Classifier: License :: OSI Approved :: MIT License
Classifier: Operating System :: OS Independent
Classifier: Development Status :: 4 - Beta
Classifier: Intended Audience :: End Users/Desktop
Classifier: Intended Audience :: Developers
Classifier: Topic :: Internet
Classifier: Topic :: Communications :: Chat
Classifier: Topic :: Utilities
Classifier: Framework :: Flask
Classifier: Natural Language :: English
Requires-Python: >=3.7
License-File: LICENSE
Dynamic: author
Dynamic: author-email
Dynamic: classifier
Dynamic: description
Dynamic: description-content-type
Dynamic: home-page
Dynamic: keywords
Dynamic: license
Dynamic: license-file
Dynamic: platform
Dynamic: project-url
Dynamic: requires-python
Dynamic: summary
